deathcomp.py
deathcomp-0.0.3.dist-info/METADATA
deathcomp-0.0.3.dist-info/WHEEL
deathcomp-0.0.3.dist-info/entry_points.txt
deathcomp-0.0.3.dist-info/top_level.txt
deathcomp-0.0.3.dist-info/RECORD
