Metadata-Version: 2.1
Name: deathcomp
Version: 0.0.3
Summary: A package compares the number of deaths due to COVID-19 in two countries
Home-page: https://github.com/RunaYoshida/deathcomp
Author: runa yoshida
Author-email: s2022067@stu.musashino-u.ac.jp
License: UNKNOWN
Project-URL: Bug Tracker, https://github.com/RunaYoshida/deathcomp
Platform: UNKNOWN
Classifier: Programming Language :: Python :: 3
Classifier: License :: OSI Approved :: MIT License
Classifier: Operating System :: OS Independent
Requires-Python: >=3.8
